lusid_drive/__init__.py
lusid_drive/api/__init__.py
lusid_drive/api/application_metadata_api.py
lusid_drive/api/files_api.py
lusid_drive/api/folders_api.py
lusid_drive/api/search_api.py
lusid_drive/api_client.py
lusid_drive/api_response.py
lusid_drive/configuration.py
lusid_drive/exceptions.py
lusid_drive/extensions/__init__.py
lusid_drive/extensions/api_client.py
lusid_drive/extensions/api_client_factory.py
lusid_drive/extensions/api_configuration.py
lusid_drive/extensions/configuration_loaders.py
lusid_drive/extensions/configuration_options.py
lusid_drive/extensions/file_access_token.py
lusid_drive/extensions/proxy_config.py
lusid_drive/extensions/refreshing_token.py
lusid_drive/extensions/rest.py
lusid_drive/extensions/retry.py
lusid_drive/extensions/socket_keep_alive.py
lusid_drive/extensions/tcp_keep_alive_connector.py
lusid_drive/models/__init__.py
lusid_drive/models/access_controlled_action.py
lusid_drive/models/access_controlled_resource.py
lusid_drive/models/action_id.py
lusid_drive/models/create_folder.py
lusid_drive/models/id_selector_definition.py
lusid_drive/models/identifier_part_schema.py
lusid_drive/models/link.py
lusid_drive/models/lusid_problem_details.py
lusid_drive/models/lusid_validation_problem_details.py
lusid_drive/models/paged_resource_list_of_storage_object.py
lusid_drive/models/resource_list_of_access_controlled_resource.py
lusid_drive/models/search_body.py
lusid_drive/models/storage_object.py
lusid_drive/models/update_file.py
lusid_drive/models/update_folder.py
lusid_drive/py.typed
lusid_drive/rest.py
lusid_drive_sdk-2.3.7.dist-info/METADATA
lusid_drive_sdk-2.3.7.dist-info/WHEEL
lusid_drive_sdk-2.3.7.dist-info/RECORD
